{
  "project_info": {
    "project_number": "1076051260859",
    "firebase_url": "https://bitwits-361ed.firebaseio.com",
    "project_id": "bitwits-361ed",
    "storage_bucket": "bitwits-361ed.appspot.com"
  },
  "client": [
    {
      "client_info": {
        "mobilesdk_app_id": "1:1076051260859:android:161e8bca1400c2bd07009e",
        "android_client_info": {
          "package_name": "com.bitwits.bitwitsapp"
        }
      },
      "oauth_client": [
        {
          "client_id": "1076051260859-hb7nkm6cm29feipthi6d8vivvt95okrk.apps.googleusercontent.com",
          "client_type": 3
        }
      ],
      "api_key": [
        {
          "current_key": "AIzaSyBKHSRV_B13X1NWsu96AOL5PY-juUPzzd4"
        }
      ],
      "services": {
        "appinvite_service": {
          "other_platform_oauth_client": [
            {
              "client_id": "1076051260859-hb7nkm6cm29feipthi6d8vivvt95okrk.apps.googleusercontent.com",
              "client_type": 3
            }
          ]
        }
      }
    }
  ],
  "configuration_version": "1"
}